datasette_auth_cookie_api/__init__.py
datasette_auth_cookie_api/cookie_api_auth.py
datasette_auth_cookie_api/utils.py
datasette_auth_cookie_api-0.2a0.dist-info/LICENSE
datasette_auth_cookie_api-0.2a0.dist-info/METADATA
datasette_auth_cookie_api-0.2a0.dist-info/WHEEL
datasette_auth_cookie_api-0.2a0.dist-info/entry_points.txt
datasette_auth_cookie_api-0.2a0.dist-info/top_level.txt
datasette_auth_cookie_api-0.2a0.dist-info/RECORD
